README.md
setup.py
PyGrids.egg-info/PKG-INFO
PyGrids.egg-info/SOURCES.txt
PyGrids.egg-info/dependency_links.txt
PyGrids.egg-info/requires.txt
PyGrids.egg-info/top_level.txt
grids/__init__.py
grids/errors.py
grids/grid.py
grids/multiarrays.py