Metadata-Version: 2.1
Name: PyGrids
Version: 1.2.0
Summary: Spreadsheet-like python objects.
Home-page: UNKNOWN
Author: Pixymon
Author-email: nlarsen23.student@gmail.com
License: UNKNOWN
Platform: UNKNOWN
